Metadata-Version: 2.1
Name: odoo-api-wrapper
Version: 0.2.3
Summary: A wrapper for Odoo's External API.
License: BSD 2-Clause License
Project-URL: Homepage, https://orabiw.github.io/odoo_api_wrapper/
Project-URL: Source, https://github.com/orabiw/odoo_api_wrapper
Keywords: odoo,xml-rpc
Requires-Python: >=3.9
License-File: LICENSE
